{"organizations":[{"id":14,"name":"Alpha Chi Omega","short_name":"AXO","category":"Sorority","url":"http://localhost:3000/organizations/14.json","booth_chairs":[{"id":51,"andrewid":"bhunttob","created_at":"2015-12-08T11:01:35.993-05:00","updated_at":"2015-12-08T11:05:26.757-05:00","has_signed_waiver":null,"phone_number":"2246009586","has_signed_hardhat_waiver":null,"user_id":null,"cached_name":"Bridget M Hunt-Tobey","cached_surname":"Hunt-Tobey","cached_email":"bhunttob@andrew.cmu.edu","cached_department":"Biological Sciences, History","cached_student_class":"Senior","cache_updated":"2015-12-08T11:05:26.754-05:00","phone_carrier_id":null},{"id":52,"andrewid":"seanders","created_at":"2015-12-08T11:01:36.012-05:00","updated_at":"2015-12-08T11:05:26.775-05:00","has_signed_waiver":null,"phone_number":"6107374187","has_signed_hardhat_waiver":null,"user_id":null,"cached_name":"Sarah E. Anderson","cached_surname":"Anderson","cached_email":"seanders@andrew.cmu.edu","cached_department":"Art","cached_student_class":null,"cache_updated":"2015-12-08T11:05:26.774-05:00","phone_carrier_id":null},{"id":53,"andrewid":"vsivakum","created_at":"2015-12-08T11:01:36.038-05:00","updated_at":"2015-12-08T11:05:26.790-05:00","has_signed_waiver":null,"phone_number":"9172444241","has_signed_hardhat_waiver":null,"user_id":null,"cached_name":"Vruti Raksha Sivakumaran","cached_surname":"Sivakumaran","cached_email":"vsivakum@andrew.cmu.edu","cached_department":"Electrical \u0026 Computer Engineering","cached_student_class":"Senior","cache_updated":"2015-12-08T11:05:26.788-05:00","phone_carrier_id":null}]},{"id":7,"name":"Alpha Epsilon Pi","short_name":"AEPi","category":"Fraternity","url":"http://localhost:3000/organizations/7.json","booth_chairs":[{"id":48,"andrewid":"bgardine","created_at":"2015-12-08T11:01:35.933-05:00","updated_at":"2015-12-08T11:04:10.206-05:00","has_signed_waiver":null,"phone_number":"7039948442","has_signed_hardhat_waiver":null,"user_id":null,"cached_name":"Bryan T Gardiner","cached_surname":"Gardiner","cached_email":"bryantgardiner@gmail.com","cached_department":"Electrical \u0026 Computer Engineering","cached_student_class":"Senior","cache_updated":"2015-12-08T11:04:10.204-05:00","phone_carrier_id":null},{"id":49,"andrewid":"gya","created_at":"2015-12-08T11:01:35.951-05:00","updated_at":"2015-12-08T11:37:45.851-05:00","has_signed_waiver":null,"phone_number":"","has_signed_hardhat_waiver":null,"user_id":null,"cached_name":"Gavriel Y. Adler","cached_surname":"Adler","cached_email":"gya@andrew.cmu.edu","cached_department":"Electrical \u0026 Computer Engineering","cached_student_class":"Masters","cache_updated":"2015-12-08T11:37:45.848-05:00","phone_carrier_id":null},{"id":50,"andrewid":"ssharea","created_at":"2015-12-08T11:01:35.975-05:00","updated_at":"2015-12-08T11:37:45.863-05:00","has_signed_waiver":null,"phone_number":"","has_signed_hardhat_waiver":null,"user_id":null,"cached_name":"N/A","cached_surname":"N/A","cached_email":"ssharea@andrew.cmu.edu","cached_department":"N/A","cached_student_class":"N/A","cache_updated":"2015-12-08T11:37:45.860-05:00","phone_carrier_id":null}]},{"id":13,"name":"Alpha Phi","short_name":"Alpha Phi","category":"Sorority","url":"http://localhost:3000/organizations/13.json","booth_chairs":[{"id":54,"andrewid":"kndu","created_at":"2015-12-08T11:01:36.057-05:00","updated_at":"2015-12-09T12:44:30.833-05:00","has_signed_waiver":null,"phone_number":"7133444667","has_signed_hardhat_waiver":null,"user_id":null,"cached_name":"Katherine N Du","cached_surname":"Du","cached_email":"kndu@andrew.cmu.edu","cached_department":"Dietrich College Interdisciplinary","cached_student_class":"Senior","cache_updated":"2015-12-09T12:44:30.831-05:00","phone_carrier_id":null},{"id":55,"andrewid":"lcody","created_at":"2015-12-08T11:01:36.072-05:00","updated_at":"2015-12-09T12:44:30.850-05:00","has_signed_waiver":null,"phone_number":"3144485994","has_signed_hardhat_waiver":null,"user_id":null,"cached_name":"Lea Katherine Cody","cached_surname":"Cody","cached_email":"lcody@andrew.cmu.edu","cached_department":"Design","cached_student_class":"Junior","cache_updated":"2015-12-09T12:44:30.848-05:00","phone_carrier_id":null},{"id":56,"andrewid":"nflorman","created_at":"2015-12-08T11:01:36.088-05:00","updated_at":"2015-12-09T12:44:30.862-05:00","has_signed_waiver":null,"phone_number":"6199522671","has_signed_hardhat_waiver":null,"user_id":null,"cached_name":"Nadia P Florman","cached_surname":"Florman","cached_email":"nflorman@andrew.cmu.edu","cached_department":"Mechanical Engineering, Engineering \u0026 Public Policy","cached_student_class":"Junior","cache_updated":"2015-12-09T12:44:30.861-05:00","phone_carrier_id":null},{"id":57,"andrewid":"vpereira","created_at":"2015-12-08T11:01:36.107-05:00","updated_at":"2015-12-09T12:44:30.877-05:00","has_signed_waiver":null,"phone_number":"","has_signed_hardhat_waiver":null,"user_id":null,"cached_name":"Victoria S Pereira","cached_surname":"Pereira","cached_email":"vpereira@andrew.cmu.edu","cached_department":"Science and Humanities Scholars, Business Administration","cached_student_class":"Senior","cache_updated":"2015-12-09T12:44:30.874-05:00","phone_carrier_id":null},{"id":58,"andrewid":"zhangw","created_at":"2015-12-08T11:01:36.121-05:00","updated_at":"2015-12-09T12:44:30.889-05:00","has_signed_waiver":null,"phone_number":"","has_signed_hardhat_waiver":null,"user_id":null,"cached_name":"Zhang Wang","cached_surname":"Wang","cached_email":"wangzh0510@gmail.com","cached_department":"Business Administration","cached_student_class":"Junior","cache_updated":"2015-12-09T12:44:30.887-05:00","phone_carrier_id":null}]},{"id":6,"name":"Alpha Phi Omega","short_name":"APhiO","category":"Concessions","url":"http://localhost:3000/organizations/6.json","booth_chairs":[{"id":59,"andrewid":"fla","created_at":"2015-12-08T11:01:36.138-05:00","updated_at":"2015-12-09T12:46:26.291-05:00","has_signed_waiver":null,"phone_number":"8143312119","has_signed_hardhat_waiver":null,"user_id":null,"cached_name":"Felicia L. Alfieri","cached_surname":"Alfieri","cached_email":"fla@andrew.cmu.edu","cached_department":"Human-Computer Interaction","cached_student_class":"Masters","cache_updated":"2015-12-09T12:46:26.288-05:00","phone_carrier_id":null}]},{"id":19,"name":"Asian Students Association","short_name":"ASA","category":"Independent","url":"http://localhost:3000/organizations/19.json","booth_chairs":[{"id":60,"andrewid":"bjli","created_at":"2015-12-08T11:01:36.154-05:00","updated_at":"2015-12-08T11:37:33.422-05:00","has_signed_waiver":null,"phone_number":"9785057460","has_signed_hardhat_waiver":null,"user_id":null,"cached_name":"Brian Li","cached_surname":"Li","cached_email":"bjli@andrew.cmu.edu","cached_department":"Human-Computer Interaction, Electrical \u0026 Computer Engineering","cached_student_class":"Junior","cache_updated":"2015-12-08T11:37:33.420-05:00","phone_carrier_id":null},{"id":61,"andrewid":"jylu","created_at":"2015-12-08T11:01:36.172-05:00","updated_at":"2015-12-08T11:37:33.440-05:00","has_signed_waiver":null,"phone_number":"6095329694","has_signed_hardhat_waiver":null,"user_id":null,"cached_name":"Jeremy Lu","cached_surname":"Lu","cached_email":"jylu@andrew.cmu.edu","cached_department":"Architecture","cached_student_class":"5th Year Senior","cache_updated":"2015-12-08T11:37:33.437-05:00","phone_carrier_id":null}]},{"id":25,"name":"Astronomy Club","short_name":"Astro","category":"Blitz","url":"http://localhost:3000/organizations/25.json","booth_chairs":[{"id":62,"andrewid":"amarano","created_at":"2015-12-08T11:01:36.191-05:00","updated_at":"2015-12-08T11:04:10.017-05:00","has_signed_waiver":null,"phone_number":"9144209281","has_signed_hardhat_waiver":null,"user_id":null,"cached_name":"Amanda Marano","cached_surname":"Marano","cached_email":"amarano@andrew.cmu.edu","cached_department":"Electrical \u0026 Computer Engineering","cached_student_class":"Senior","cache_updated":"2015-12-08T11:04:10.016-05:00","phone_carrier_id":null},{"id":63,"andrewid":"oce","created_at":"2015-12-08T11:01:36.212-05:00","updated_at":"2015-12-09T12:44:54.885-05:00","has_signed_waiver":null,"phone_number":"2675950677","has_signed_hardhat_waiver":null,"user_id":null,"cached_name":"Onyenma Enwereji","cached_surname":"Enwereji","cached_email":"oce@andrew.cmu.edu","cached_department":"Chemical Engineering, Biomedical Engineering","cached_student_class":"Senior","cache_updated":"2015-12-09T12:44:54.883-05:00","phone_carrier_id":null}]},{"id":32,"name":"Crew","short_name":"Crew","category":"Non-Building","url":"http://localhost:3000/organizations/32.json","booth_chairs":[]},{"id":15,"name":"Delta Delta Delta","short_name":"Tri Delt","category":"Sorority","url":"http://localhost:3000/organizations/15.json","booth_chairs":[{"id":64,"andrewid":"gjackson","created_at":"2015-12-08T11:01:36.232-05:00","updated_at":"2015-12-09T12:46:26.316-05:00","has_signed_waiver":null,"phone_number":"4124207887","has_signed_hardhat_waiver":null,"user_id":null,"cached_name":"Geneva Jackson","cached_surname":"Jackson","cached_email":"gjackson@andrew.cmu.edu","cached_department":"History","cached_student_class":"Senior","cache_updated":"2015-12-09T12:46:26.314-05:00","phone_carrier_id":null},{"id":65,"andrewid":"csharkey","created_at":"2015-12-08T11:01:36.248-05:00","updated_at":"2015-12-10T18:47:13.788-05:00","has_signed_waiver":null,"phone_number":"6142579397","has_signed_hardhat_waiver":null,"user_id":null,"cached_name":"Caitlin Sharkey","cached_surname":"Sharkey","cached_email":"csharkey@andrew.cmu.edu","cached_department":"Mechanical Engineering","cached_student_class":null,"cache_updated":"2015-12-10T18:47:13.769-05:00","phone_carrier_id":null},{"id":66,"andrewid":"smosshor","created_at":"2015-12-08T11:01:36.263-05:00","updated_at":"2015-12-09T12:46:28.676-05:00","has_signed_waiver":null,"phone_number":"","has_signed_hardhat_waiver":null,"user_id":null,"cached_name":"Sarah Moss-Horwitz","cached_surname":"Moss-Horwitz","cached_email":"smosshor@andrew.cmu.edu","cached_department":"Social \u0026 Decision Sciences, Human-Computer Interaction","cached_student_class":"Junior","cache_updated":"2015-12-09T12:46:28.673-05:00","phone_carrier_id":null}]},{"id":16,"name":"Delta Gamma","short_name":"DG","category":"Sorority","url":"http://localhost:3000/organizations/16.json","booth_chairs":[{"id":67,"andrewid":"atjones","created_at":"2015-12-08T11:01:36.278-05:00","updated_at":"2015-12-08T11:04:10.179-05:00","has_signed_waiver":null,"phone_number":"4438444424","has_signed_hardhat_waiver":null,"user_id":null,"cached_name":"Amelia T Jones","cached_surname":"Jones","cached_email":"atjones@andrew.cmu.edu","cached_department":"Civil \u0026 Environmental Engineering","cached_student_class":"Senior","cache_updated":"2015-12-08T11:04:10.178-05:00","phone_carrier_id":null},{"id":68,"andrewid":"casantil","created_at":"2015-12-08T11:01:36.293-05:00","updated_at":"2015-12-10T18:47:13.813-05:00","has_signed_waiver":null,"phone_number":"6104208343","has_signed_hardhat_waiver":null,"user_id":null,"cached_name":"Caroline Santilli","cached_surname":"Santilli","cached_email":"casantil@andrew.cmu.edu","cached_department":"Humanities and Arts","cached_student_class":"Junior","cache_updated":"2015-12-10T18:47:13.810-05:00","phone_carrier_id":null},{"id":69,"andrewid":"elawlis","created_at":"2015-12-08T11:01:36.310-05:00","updated_at":"2015-12-09T12:46:26.276-05:00","has_signed_waiver":null,"phone_number":"8326930740","has_signed_hardhat_waiver":null,"user_id":null,"cached_name":"Emily E Lawlis","cached_surname":"Lawlis","cached_email":"elawlis@andrew.cmu.edu","cached_department":"Chemistry","cached_student_class":"Senior","cache_updated":"2015-12-09T12:46:26.274-05:00","phone_carrier_id":null},{"id":70,"andrewid":"lcwillia","created_at":"2015-12-08T11:01:36.329-05:00","updated_at":"2015-12-10T18:47:13.833-05:00","has_signed_waiver":null,"phone_number":"2677461544","has_signed_hardhat_waiver":null,"user_id":null,"cached_name":"Leslie Williams","cached_surname":"Williams","cached_email":"lcwillia@andrew.cmu.edu","cached_department":"Business Administration","cached_student_class":"Junior","cache_updated":"2015-12-10T18:47:13.831-05:00","phone_carrier_id":null},{"id":71,"andrewid":"tyv","created_at":"2015-12-08T11:01:36.352-05:00","updated_at":"2015-12-09T12:46:28.788-05:00","has_signed_waiver":null,"phone_number":"6469431119","has_signed_hardhat_waiver":null,"user_id":null,"cached_name":"Taisha Y. Vargas","cached_surname":"Vargas","cached_email":"tyv@andrew.cmu.edu","cached_department":"Mechanical Engineering","cached_student_class":"Senior","cache_updated":"2015-12-09T12:46:28.786-05:00","phone_carrier_id":null}]},{"id":8,"name":"Delta Tau Delta","short_name":"DTD","category":"Fraternity","url":"http://localhost:3000/organizations/8.json","booth_chairs":[{"id":72,"andrewid":"aperley","created_at":"2015-12-08T11:01:36.375-05:00","updated_at":"2015-12-08T11:04:10.135-05:00","has_signed_waiver":null,"phone_number":"7202522781","has_signed_hardhat_waiver":null,"user_id":null,"cached_name":"Aaron Perley","cached_surname":"Perley","cached_email":"aperley@andrew.cmu.edu","cached_department":"Electrical \u0026 Computer Engineering, Robotics","cached_student_class":"Junior","cache_updated":"2015-12-08T11:04:10.133-05:00","phone_carrier_id":null},{"id":73,"andrewid":"achisolm","created_at":"2015-12-08T11:01:36.402-05:00","updated_at":"2015-12-08T11:04:09.956-05:00","has_signed_waiver":null,"phone_number":"6315468835","has_signed_hardhat_waiver":null,"user_id":null,"cached_name":"Alexander C Chisolm","cached_surname":"Chisolm","cached_email":"achisolm@andrew.cmu.edu","cached_department":"Dietrich College Interdisciplinary","cached_student_class":null,"cache_updated":"2015-12-08T11:04:09.954-05:00","phone_carrier_id":null},{"id":74,"andrewid":"haozheg","created_at":"2015-12-08T11:01:36.419-05:00","updated_at":"2015-12-09T12:45:04.455-05:00","has_signed_waiver":null,"phone_number":"9084034261","has_signed_hardhat_waiver":null,"user_id":null,"cached_name":"Haozhe Gao","cached_surname":"Gao","cached_email":"haozheg@andrew.cmu.edu","cached_department":"Computer Science","cached_student_class":null,"cache_updated":"2015-12-09T12:45:04.453-05:00","phone_carrier_id":null},{"id":75,"andrewid":"rmckinne","created_at":"2015-12-08T11:01:36.436-05:00","updated_at":"2015-12-09T12:45:04.474-05:00","has_signed_waiver":null,"phone_number":"9419141174","has_signed_hardhat_waiver":null,"user_id":null,"cached_name":"Ryan McKinney","cached_surname":"McKinney","cached_email":"rmckinne@andrew.cmu.edu","cached_department":"Chemical Engineering","cached_student_class":"Senior","cache_updated":"2015-12-09T12:45:04.470-05:00","phone_carrier_id":null},{"id":76,"andrewid":"tfs","created_at":"2015-12-08T11:01:36.455-05:00","updated_at":"2015-12-09T12:45:04.489-05:00","has_signed_waiver":null,"phone_number":"7173195528","has_signed_hardhat_waiver":null,"user_id":null,"cached_name":"Thomas F Sterling","cached_surname":"Sterling","cached_email":"Tsterling93@gmail.com","cached_department":"Architecture","cached_student_class":"5th Year Senior","cache_updated":"2015-12-09T12:45:04.487-05:00","phone_carrier_id":null},{"id":116,"andrewid":"rpwhite","created_at":"2015-12-08T11:01:39.750-05:00","updated_at":"2015-12-09T12:45:04.504-05:00","has_signed_waiver":null,"phone_number":"1713435788","has_signed_hardhat_waiver":null,"user_id":8,"cached_name":"Robert Patrick White","cached_surname":"White","cached_email":"rpwhite@andrew.cmu.edu","cached_department":null,"cached_student_class":null,"cache_updated":"2015-12-09T12:45:04.501-05:00","phone_carrier_id":null}]},{"id":9,"name":"Delta Upsilon","short_name":"DU","category":"Fraternity","url":"http://localhost:3000/organizations/9.json","booth_chairs":[]},{"id":2,"name":"Environmental Health and Safety","short_name":"EH\u0026S","category":"Staff","url":"http://localhost:3000/organizations/2.json","booth_chairs":[]},{"id":3,"name":"Facilities Management Services","short_name":"FMS","category":"Staff","url":"http://localhost:3000/organizations/3.json","booth_chairs":[]},{"id":20,"name":"Fringe","short_name":"Fringe","category":"Independent","url":"http://localhost:3000/organizations/20.json","booth_chairs":[{"id":77,"andrewid":"jacobbro","created_at":"2015-12-08T11:01:36.471-05:00","updated_at":"2015-12-09T12:46:26.363-05:00","has_signed_waiver":null,"phone_number":"5037479771","has_signed_hardhat_waiver":null,"user_id":null,"cached_name":"Jacob L Brooks","cached_surname":"Brooks","cached_email":"jacobbro@andrew.cmu.edu","cached_department":"Electrical \u0026 Computer Engineering","cached_student_class":"Junior","cache_updated":"2015-12-09T12:46:26.361-05:00","phone_carrier_id":null},{"id":78,"andrewid":"jzak","created_at":"2015-12-08T11:01:36.486-05:00","updated_at":"2015-12-10T18:47:13.853-05:00","has_signed_waiver":null,"phone_number":"4127351981","has_signed_hardhat_waiver":null,"user_id":null,"cached_name":"Joshua Joseph Zak","cached_surname":"Zak","cached_email":"jzak@andrew.cmu.edu","cached_department":"Science and Humanities Scholars","cached_student_class":"Junior","cache_updated":"2015-12-10T18:47:13.851-05:00","phone_carrier_id":null},{"id":79,"andrewid":"kkwilkin","created_at":"2015-12-08T11:01:36.501-05:00","updated_at":"2015-12-10T18:47:13.868-05:00","has_signed_waiver":null,"phone_number":"7077380375","has_signed_hardhat_waiver":null,"user_id":null,"cached_name":"Kaitlin Wilkinson","cached_surname":"Wilkinson","cached_email":"kkwilkin@andrew.cmu.edu","cached_department":"Design","cached_student_class":"Junior","cache_updated":"2015-12-10T18:47:13.865-05:00","phone_carrier_id":null}]},{"id":36,"name":"Habitat for Humanity","short_name":"Habitat","category":"Non-Building","url":"http://localhost:3000/organizations/36.json","booth_chairs":[]},{"id":21,"name":"KGB","short_name":"KGB","category":"Independent","url":"http://localhost:3000/organizations/21.json","booth_chairs":[{"id":91,"andrewid":"sctoor","created_at":"2015-12-08T11:01:36.704-05:00","updated_at":"2015-12-10T18:47:13.884-05:00","has_signed_waiver":null,"phone_number":"7033029956","has_signed_hardhat_waiver":null,"user_id":null,"cached_name":"Skye C Toor","cached_surname":"Toor","cached_email":"stoor@cmu.edu","cached_department":"Statistics","cached_student_class":"Junior","cache_updated":"2015-12-10T18:47:13.882-05:00","phone_carrier_id":null},{"id":92,"andrewid":"sguertin","created_at":"2015-12-08T11:01:36.724-05:00","updated_at":"2015-12-09T12:46:28.658-05:00","has_signed_waiver":null,"phone_number":"8029893063","has_signed_hardhat_waiver":null,"user_id":null,"cached_name":"Stuart W Guertin","cached_surname":"Guertin","cached_email":"sguertin@andrew.cmu.edu","cached_department":"Computer Science","cached_student_class":"Senior","cache_updated":"2015-12-09T12:46:28.655-05:00","phone_carrier_id":null}]},{"id":17,"name":"Kappa Alpha Theta","short_name":"Theta","category":"Sorority","url":"http://localhost:3000/organizations/17.json","booth_chairs":[{"id":80,"andrewid":"aritchie","created_at":"2015-12-08T11:01:36.516-05:00","updated_at":"2015-12-08T11:04:10.164-05:00","has_signed_waiver":null,"phone_number":"2155108559","has_signed_hardhat_waiver":null,"user_id":null,"cached_name":"Annette K Ritchie","cached_surname":"Ritchie","cached_email":"annette2151@gmail.com","cached_department":"Materials Science \u0026 Engineering, Biomedical Engineering","cached_student_class":"Senior","cache_updated":"2015-12-08T11:04:10.162-05:00","phone_carrier_id":null},{"id":81,"andrewid":"ihlee","created_at":"2015-12-08T11:01:36.534-05:00","updated_at":"2015-12-09T12:46:26.349-05:00","has_signed_waiver":null,"phone_number":"9713408528","has_signed_hardhat_waiver":null,"user_id":null,"cached_name":"Irene H. Lee","cached_surname":"Lee","cached_email":"ihlee@andrew.cmu.edu","cached_department":"Mechanical Engineering","cached_student_class":"Senior","cache_updated":"2015-12-09T12:46:26.347-05:00","phone_carrier_id":null},{"id":82,"andrewid":"rwolfing","created_at":"2015-12-08T11:01:36.553-05:00","updated_at":"2015-12-10T18:47:13.905-05:00","has_signed_waiver":null,"phone_number":"9259897941","has_signed_hardhat_waiver":null,"user_id":null,"cached_name":"Rebecca Wolfinger","cached_surname":"Wolfinger","cached_email":"rwolfing@andrew.cmu.edu","cached_department":"Electrical \u0026 Computer Engineering","cached_student_class":"Senior","cache_updated":"2015-12-10T18:47:13.902-05:00","phone_carrier_id":null},{"id":83,"andrewid":"snarburg","created_at":"2015-12-08T11:01:36.569-05:00","updated_at":"2015-12-09T12:46:28.766-05:00","has_signed_waiver":null,"phone_number":"6094770540","has_signed_hardhat_waiver":null,"user_id":null,"cached_name":"Sarah Narburgh","cached_surname":"Narburgh","cached_email":"snarburg@andrew.cmu.edu","cached_department":"Chemical Engineering","cached_student_class":"Masters","cache_updated":"2015-12-09T12:46:28.764-05:00","phone_carrier_id":null}]},{"id":18,"name":"Kappa Kappa Gamma","short_name":"Kappa","category":"Sorority","url":"http://localhost:3000/organizations/18.json","booth_chairs":[{"id":84,"andrewid":"amcnulty","created_at":"2015-12-08T11:01:36.584-05:00","updated_at":"2015-12-08T11:04:10.096-05:00","has_signed_waiver":null,"phone_number":"7816904444","has_signed_hardhat_waiver":null,"user_id":null,"cached_name":"Alison R McNulty","cached_surname":"McNulty","cached_email":"amcnulty@andrew.cmu.edu","cached_department":"Mechanical Engineering","cached_student_class":"5th Year Senior","cache_updated":"2015-12-08T11:04:10.093-05:00","phone_carrier_id":null},{"id":85,"andrewid":"acrigler","created_at":"2015-12-08T11:01:36.602-05:00","updated_at":"2015-12-08T11:04:09.969-05:00","has_signed_waiver":null,"phone_number":"2038324033","has_signed_hardhat_waiver":null,"user_id":null,"cached_name":"Amelia Crigler","cached_surname":"Crigler","cached_email":"acrigler@andrew.cmu.edu","cached_department":"Computer Science, Philosophy","cached_student_class":"Senior","cache_updated":"2015-12-08T11:04:09.967-05:00","phone_carrier_id":null},{"id":86,"andrewid":"clohman","created_at":"2015-12-08T11:01:36.620-05:00","updated_at":"2015-12-10T18:47:13.930-05:00","has_signed_waiver":null,"phone_number":"3109717909","has_signed_hardhat_waiver":null,"user_id":null,"cached_name":"Caitlin M Lohman","cached_surname":"Lohman","cached_email":"clohman@andrew.cmu.edu","cached_department":"Philosophy","cached_student_class":"Senior","cache_updated":"2015-12-10T18:47:13.926-05:00","phone_carrier_id":null},{"id":87,"andrewid":"jry","created_at":"2015-12-08T11:01:36.636-05:00","updated_at":"2015-12-10T18:47:13.957-05:00","has_signed_waiver":null,"phone_number":"6107376024","has_signed_hardhat_waiver":null,"user_id":null,"cached_name":"Jennifer Young","cached_surname":"Young","cached_email":"jry@andrew.cmu.edu","cached_department":"Civil \u0026 Environmental Engineering, Architecture","cached_student_class":"5th Year Senior","cache_updated":"2015-12-10T18:47:13.952-05:00","phone_carrier_id":null}]},{"id":5,"name":"Kappa Sigma","short_name":"KapSig","category":"Concessions","url":"http://localhost:3000/organizations/5.json","booth_chairs":[{"id":88,"andrewid":"efiedore","created_at":"2015-12-08T11:01:36.653-05:00","updated_at":"2015-12-09T12:45:12.597-05:00","has_signed_waiver":null,"phone_number":"7138066105","has_signed_hardhat_waiver":null,"user_id":null,"cached_name":"Eric S Fiedorek","cached_surname":"Fiedorek","cached_email":"efiedore@andrew.cmu.edu","cached_department":"Social \u0026 Decision Sciences","cached_student_class":"Junior","cache_updated":"2015-12-09T12:45:12.594-05:00","phone_carrier_id":null},{"id":89,"andrewid":"jbarry","created_at":"2015-12-08T11:01:36.673-05:00","updated_at":"2015-12-09T12:45:12.613-05:00","has_signed_waiver":null,"phone_number":"2403837698","has_signed_hardhat_waiver":null,"user_id":null,"cached_name":"John P Barry","cached_surname":"Barry","cached_email":"jbarry@andrew.cmu.edu","cached_department":"Mechanical Engineering","cached_student_class":"Senior","cache_updated":"2015-12-09T12:45:12.611-05:00","phone_carrier_id":null},{"id":90,"andrewid":"ajcollin","created_at":"2015-12-08T11:01:36.687-05:00","updated_at":"2015-12-08T11:04:09.982-05:00","has_signed_waiver":null,"phone_number":"","has_signed_hardhat_waiver":null,"user_id":null,"cached_name":"Aaron J Collins","cached_surname":"Collins","cached_email":"ajcollin@andrew.cmu.edu","cached_department":"Mechanical Engineering","cached_student_class":"Junior","cache_updated":"2015-12-08T11:04:09.981-05:00","phone_carrier_id":null}]},{"id":37,"name":"Lunar Gala","short_name":"LG","category":"Non-Building","url":"http://localhost:3000/organizations/37.json","booth_chairs":[]},{"id":26,"name":"Math Club","short_name":"Math Club","category":"Blitz","url":"http://localhost:3000/organizations/26.json","booth_chairs":[{"id":93,"andrewid":"anqiwang","created_at":"2015-12-08T11:01:36.740-05:00","updated_at":"2015-12-08T11:04:10.123-05:00","has_signed_waiver":null,"phone_number":"4123706158","has_signed_hardhat_waiver":null,"user_id":null,"cached_name":"Anqi Wang","cached_surname":"Wang","cached_email":"anqiwang@andrew.cmu.edu","cached_department":"Mathematical Sciences","cached_student_class":"Junior","cache_updated":"2015-12-08T11:04:10.122-05:00","phone_carrier_id":null},{"id":94,"andrewid":"colinkel","created_at":"2015-12-08T11:01:36.760-05:00","updated_at":"2015-12-10T18:47:13.988-05:00","has_signed_waiver":null,"phone_number":"5714490561","has_signed_hardhat_waiver":null,"user_id":null,"cached_name":"Colin E Kelly","cached_surname":"Kelly","cached_email":"colinkel@andrew.cmu.edu","cached_department":"Mathematical Sciences","cached_student_class":"Sophomore","cache_updated":"2015-12-10T18:47:13.985-05:00","phone_carrier_id":null},{"id":95,"andrewid":"dmehrle","created_at":"2015-12-08T11:01:36.776-05:00","updated_at":"2015-12-10T18:47:14.126-05:00","has_signed_waiver":null,"phone_number":"6144588176","has_signed_hardhat_waiver":null,"user_id":null,"cached_name":"David F. Mehrle","cached_surname":"Mehrle","cached_email":"dmehrle@cmu.edu","cached_department":"Mathematical Sciences","cached_student_class":null,"cache_updated":"2015-12-10T18:47:14.124-05:00","phone_carrier_id":null},{"id":96,"andrewid":"kborst","created_at":"2015-12-08T11:01:36.792-05:00","updated_at":"2015-12-10T18:47:14.138-05:00","has_signed_waiver":null,"phone_number":"9143299391","has_signed_hardhat_waiver":null,"user_id":null,"cached_name":"Katherine R Borst","cached_surname":"Borst","cached_email":"kborst@cmu.edu","cached_department":"Mathematical Sciences","cached_student_class":"Junior","cache_updated":"2015-12-10T18:47:14.136-05:00","phone_carrier_id":null},{"id":97,"andrewid":"zng","created_at":"2015-12-08T11:01:36.808-05:00","updated_at":"2015-12-09T12:46:28.807-05:00","has_signed_waiver":null,"phone_number":"4434735523","has_signed_hardhat_waiver":null,"user_id":null,"cached_name":"Zachary N. Greenberg","cached_surname":"Greenberg","cached_email":"zng@cmu.edu","cached_department":"Mathematical Sciences","cached_student_class":null,"cache_updated":"2015-12-09T12:46:28.805-05:00","phone_carrier_id":null}]},{"id":27,"name":"Mayur SASA","short_name":"Mayur","category":"Blitz","url":"http://localhost:3000/organizations/27.json","booth_chairs":[{"id":98,"andrewid":"gauryn","created_at":"2015-12-08T11:01:36.832-05:00","updated_at":"2015-12-09T12:46:26.304-05:00","has_signed_waiver":null,"phone_number":"4123200623","has_signed_hardhat_waiver":null,"user_id":null,"cached_name":"Gaury Nagaraju","cached_surname":"Nagaraju","cached_email":"gauryn@andrew.cmu.edu","cached_department":"Dietrich College Interdisciplinary","cached_student_class":"Junior","cache_updated":"2015-12-09T12:46:26.302-05:00","phone_carrier_id":null}]},{"id":28,"name":"Mellon College of Science","short_name":"MCS","category":"Blitz","url":"http://localhost:3000/organizations/28.json","booth_chairs":[{"id":99,"andrewid":"kaitlinh","created_at":"2015-12-08T11:01:36.854-05:00","updated_at":"2015-12-10T18:47:14.156-05:00","has_signed_waiver":null,"phone_number":"9142153025","has_signed_hardhat_waiver":null,"user_id":null,"cached_name":"Kaitlin Hamilton","cached_surname":"Hamilton","cached_email":"kaitlinh@andrew.cmu.edu","cached_department":"Biological Sciences","cached_student_class":null,"cache_updated":"2015-12-10T18:47:14.153-05:00","phone_carrier_id":null},{"id":100,"andrewid":"jiyunkwo","created_at":"2015-12-08T11:01:36.873-05:00","updated_at":"2015-12-09T12:46:26.399-05:00","has_signed_waiver":null,"phone_number":"4128633273","has_signed_hardhat_waiver":null,"user_id":null,"cached_name":"Ji Yun Kwon","cached_surname":"Kwon","cached_email":"jiyunkwo@andrew.cmu.edu","cached_department":"Physics","cached_student_class":"Junior","cache_updated":"2015-12-09T12:46:26.397-05:00","phone_carrier_id":null}]},{"id":10,"name":"Phi Delta Theta","short_name":"PhiDelt","category":"Fraternity","url":"http://localhost:3000/organizations/10.json","booth_chairs":[{"id":101,"andrewid":"resposit","created_at":"2015-12-08T11:01:36.895-05:00","updated_at":"2015-12-09T12:45:48.729-05:00","has_signed_waiver":null,"phone_number":"","has_signed_hardhat_waiver":null,"user_id":null,"cached_name":"Robert James Esposito","cached_surname":"Esposito","cached_email":"resposit@andrew.cmu.edu","cached_department":"Architecture","cached_student_class":"Senior","cache_updated":"2015-12-09T12:45:48.727-05:00","phone_carrier_id":null}]},{"id":34,"name":"Pi Kappa Alpha","short_name":"Pike","category":"Non-Building","url":"http://localhost:3000/organizations/34.json","booth_chairs":[]},{"id":11,"name":"Sigma Alpha Epsilon","short_name":"SAE","category":"Fraternity","url":"http://localhost:3000/organizations/11.json","booth_chairs":[{"id":103,"andrewid":"ambaker","created_at":"2015-12-08T11:01:36.928-05:00","updated_at":"2015-12-08T11:04:10.065-05:00","has_signed_waiver":null,"phone_number":"4125267380","has_signed_hardhat_waiver":null,"user_id":null,"cached_name":"Alex M Baker","cached_surname":"Baker","cached_email":"ambaker@andrew.cmu.edu","cached_department":"Mechanical Engineering","cached_student_class":"Senior","cache_updated":"2015-12-08T11:04:10.062-05:00","phone_carrier_id":null},{"id":104,"andrewid":"kschin","created_at":"2015-12-08T11:01:36.946-05:00","updated_at":"2015-12-10T18:47:14.172-05:00","has_signed_waiver":null,"phone_number":"6319884058","has_signed_hardhat_waiver":null,"user_id":null,"cached_name":"Kenneth S Chin","cached_surname":"Chin","cached_email":"kschin@andrew.cmu.edu","cached_department":"Materials Science \u0026 Engineering","cached_student_class":"Senior","cache_updated":"2015-12-10T18:47:14.170-05:00","phone_carrier_id":null},{"id":105,"andrewid":"drmorale","created_at":"2015-12-08T11:01:36.964-05:00","updated_at":"2015-12-10T18:47:14.184-05:00","has_signed_waiver":null,"phone_number":"","has_signed_hardhat_waiver":null,"user_id":null,"cached_name":"Dennys R Morales","cached_surname":"Morales","cached_email":"drmorale@andrew.cmu.edu","cached_department":"Mechanical Engineering","cached_student_class":"Senior","cache_updated":"2015-12-10T18:47:14.182-05:00","phone_carrier_id":null}]},{"id":31,"name":"Sigma Chi","short_name":"SigChi","category":"Blitz","url":"http://localhost:3000/organizations/31.json","booth_chairs":[{"id":106,"andrewid":"pdominic","created_at":"2015-12-08T11:01:36.980-05:00","updated_at":"2015-12-10T18:47:14.203-05:00","has_signed_waiver":null,"phone_number":"9788534116","has_signed_hardhat_waiver":null,"user_id":null,"cached_name":"Philip T Dominici","cached_surname":"Dominici","cached_email":"pdominic@andrew.cmu.edu","cached_department":"Science and Humanities Scholars","cached_student_class":"Junior","cache_updated":"2015-12-10T18:47:14.199-05:00","phone_carrier_id":null}]},{"id":12,"name":"Sigma Phi Epsilon","short_name":"SigEp","category":"Fraternity","url":"http://localhost:3000/organizations/12.json","booth_chairs":[{"id":107,"andrewid":"bsiegel","created_at":"2015-12-08T11:01:36.995-05:00","updated_at":"2015-12-08T11:03:36.452-05:00","has_signed_waiver":null,"phone_number":"2074752240","has_signed_hardhat_waiver":null,"user_id":null,"cached_name":"Benjamin Siegel","cached_surname":"Siegel","cached_email":"bsiegel@andrew.cmu.edu","cached_department":"Electrical \u0026 Computer Engineering","cached_student_class":"Masters","cache_updated":"2015-12-08T11:03:36.439-05:00","phone_carrier_id":null},{"id":108,"andrewid":"sjstark","created_at":"2015-12-08T11:01:37.010-05:00","updated_at":"2015-12-08T11:03:36.486-05:00","has_signed_waiver":null,"phone_number":"9049622490","has_signed_hardhat_waiver":null,"user_id":null,"cached_name":"Samuel Stark","cached_surname":"Stark","cached_email":"sjstark@andrew.cmu.edu","cached_department":"Drama","cached_student_class":"Junior","cache_updated":"2015-12-08T11:03:36.482-05:00","phone_carrier_id":null}]},{"id":23,"name":"Singapore Students Association","short_name":"SSA","category":"Independent","url":"http://localhost:3000/organizations/23.json","booth_chairs":[{"id":110,"andrewid":"zunyibrt","created_at":"2015-12-08T11:01:37.045-05:00","updated_at":"2015-12-09T12:46:28.822-05:00","has_signed_waiver":null,"phone_number":"4125195516","has_signed_hardhat_waiver":null,"user_id":null,"cached_name":"Zun Yi Brent Brent Tan","cached_surname":"Tan","cached_email":"zunyibrt@andrew.cmu.edu","cached_department":"Science and Humanities Scholars","cached_student_class":"Junior","cache_updated":"2015-12-09T12:46:28.820-05:00","phone_carrier_id":null},{"id":111,"andrewid":"jechua","created_at":"2015-12-08T11:01:37.062-05:00","updated_at":"2015-12-09T12:46:26.378-05:00","has_signed_waiver":null,"phone_number":"4126239206","has_signed_hardhat_waiver":null,"user_id":null,"cached_name":"Jane E Chua","cached_surname":"Chua","cached_email":"janechua@cmu.edu","cached_department":"Computer Science","cached_student_class":"Junior","cache_updated":"2015-12-09T12:46:26.376-05:00","phone_carrier_id":null}]},{"id":29,"name":"Spirit","short_name":"Spirit","category":"Blitz","url":"http://localhost:3000/organizations/29.json","booth_chairs":[{"id":109,"andrewid":"jmonroe","created_at":"2015-12-08T11:01:37.029-05:00","updated_at":"2015-12-10T18:47:14.222-05:00","has_signed_waiver":null,"phone_number":"2035814082","has_signed_hardhat_waiver":null,"user_id":null,"cached_name":"James V Monroe","cached_surname":"Monroe","cached_email":"jmonroe@andrew.cmu.edu","cached_department":"Architecture","cached_student_class":"Junior","cache_updated":"2015-12-10T18:47:14.220-05:00","phone_carrier_id":null}]},{"id":1,"name":"Spring Carnival Committee","short_name":"SCC","category":"SCC","url":"http://localhost:3000/organizations/1.json","booth_chairs":[{"id":1,"andrewid":"cweintra","created_at":"2015-12-08T11:01:34.924-05:00","updated_at":"2015-12-08T11:14:47.951-05:00","has_signed_waiver":null,"phone_number":"2038309156","has_signed_hardhat_waiver":null,"user_id":1,"cached_name":"Carrie Weintraub","cached_surname":"Weintraub","cached_email":"cweintra@andrew.cmu.edu","cached_department":"Dietrich College Interdisciplinary","cached_student_class":null,"cache_updated":"2015-12-08T11:14:47.948-05:00","phone_carrier_id":null},{"id":2,"andrewid":"arakla","created_at":"2015-12-08T11:01:35.000-05:00","updated_at":"2015-12-08T11:37:00.427-05:00","has_signed_waiver":null,"phone_number":"2817692637","has_signed_hardhat_waiver":null,"user_id":2,"cached_name":"Aamer Rakla","cached_surname":"Rakla","cached_email":"arakla@cmu.edu","cached_department":"Humanities and Arts","cached_student_class":"Senior","cache_updated":"2015-12-08T11:04:10.146-05:00","phone_carrier_id":null},{"id":3,"andrewid":"hmostert","created_at":"2015-12-08T11:01:35.044-05:00","updated_at":"2015-12-08T11:05:26.824-05:00","has_signed_waiver":null,"phone_number":"1234567890","has_signed_hardhat_waiver":null,"user_id":3,"cached_name":"Hannelie Mostert","cached_surname":"Mostert","cached_email":"hmostert@andrew.cmu.edu","cached_department":"Civil \u0026 Environmental Engineering","cached_student_class":null,"cache_updated":"2015-12-08T11:05:26.822-05:00","phone_carrier_id":null},{"id":4,"andrewid":"rcrown","created_at":"2015-12-08T11:01:35.088-05:00","updated_at":"2015-12-09T12:50:38.223-05:00","has_signed_waiver":true,"phone_number":"2817692637","has_signed_hardhat_waiver":null,"user_id":4,"cached_name":"Rachel J Crown","cached_surname":"Crown","cached_email":"rcrown@andrew.cmu.edu","cached_department":null,"cached_student_class":null,"cache_updated":"2015-12-08T11:14:48.261-05:00","phone_carrier_id":1},{"id":5,"andrewid":"leonardt","created_at":"2015-12-08T11:01:35.125-05:00","updated_at":"2015-12-08T11:14:48.105-05:00","has_signed_waiver":null,"phone_number":"4122688704","has_signed_hardhat_waiver":null,"user_id":5,"cached_name":"Timothy Leonard","cached_surname":"Leonard","cached_email":"leonardt@andrew.cmu.edu","cached_department":"Alumni Relations (Univ Advancement)","cached_student_class":null,"cache_updated":"2015-12-08T11:14:48.103-05:00","phone_carrier_id":null}]},{"id":4,"name":"Student Affairs","short_name":"DOSA","category":"Staff","url":"http://localhost:3000/organizations/4.json","booth_chairs":[{"id":5,"andrewid":"leonardt","created_at":"2015-12-08T11:01:35.125-05:00","updated_at":"2015-12-08T11:14:48.105-05:00","has_signed_waiver":null,"phone_number":"4122688704","has_signed_hardhat_waiver":null,"user_id":5,"cached_name":"Timothy Leonard","cached_surname":"Leonard","cached_email":"leonardt@andrew.cmu.edu","cached_department":"Alumni Relations (Univ Advancement)","cached_student_class":null,"cache_updated":"2015-12-08T11:14:48.103-05:00","phone_carrier_id":null}]},{"id":22,"name":"Student Dormitory Council","short_name":"SDC","category":"Independent","url":"http://localhost:3000/organizations/22.json","booth_chairs":[{"id":102,"andrewid":"kswarts","created_at":"2015-12-08T11:01:36.911-05:00","updated_at":"2015-12-08T11:38:03.084-05:00","has_signed_waiver":null,"phone_number":"5702491340","has_signed_hardhat_waiver":null,"user_id":null,"cached_name":"Kristine H. Swarts","cached_surname":"Swarts","cached_email":"kristinehswarts@gmail.com","cached_department":"History","cached_student_class":null,"cache_updated":"2015-12-08T11:38:03.082-05:00","phone_carrier_id":null}]},{"id":30,"name":"Sustainable Earth","short_name":"Sust. Earth","category":"Blitz","url":"http://localhost:3000/organizations/30.json","booth_chairs":[{"id":112,"andrewid":"alexchen","created_at":"2015-12-08T11:01:37.077-05:00","updated_at":"2015-12-08T11:04:10.005-05:00","has_signed_waiver":null,"phone_number":"6308095728","has_signed_hardhat_waiver":null,"user_id":null,"cached_name":"Alex Y. Chen","cached_surname":"Chen","cached_email":"alexchen@andrew.cmu.edu","cached_department":"Materials Science \u0026 Engineering","cached_student_class":"Junior","cache_updated":"2015-12-08T11:04:10.003-05:00","phone_carrier_id":null},{"id":113,"andrewid":"htomio","created_at":"2015-12-08T11:01:37.092-05:00","updated_at":"2015-12-09T12:46:26.333-05:00","has_signed_waiver":null,"phone_number":"3126622539","has_signed_hardhat_waiver":null,"user_id":null,"cached_name":"Hannah Tomio","cached_surname":"Tomio","cached_email":"htomio@andrew.cmu.edu","cached_department":"Electrical \u0026 Computer Engineering, Modern Languages","cached_student_class":"Junior","cache_updated":"2015-12-09T12:46:26.331-05:00","phone_carrier_id":null}]},{"id":24,"name":"Taiwanese Students Association","short_name":"TSA","category":"Independent","url":"http://localhost:3000/organizations/24.json","booth_chairs":[{"id":114,"andrewid":"kywang1","created_at":"2015-12-08T11:01:37.107-05:00","updated_at":"2015-12-09T12:45:30.348-05:00","has_signed_waiver":null,"phone_number":"8583662883","has_signed_hardhat_waiver":null,"user_id":null,"cached_name":"Kevin Y Wang","cached_surname":"Wang","cached_email":"kywang1@andrew.cmu.edu","cached_department":"Mechanical Engineering","cached_student_class":"Junior","cache_updated":"2015-12-09T12:45:30.346-05:00","phone_carrier_id":null},{"id":115,"andrewid":"hsienhsi","created_at":"2015-12-08T11:01:37.125-05:00","updated_at":"2015-12-09T12:45:30.360-05:00","has_signed_waiver":null,"phone_number":"4123528929","has_signed_hardhat_waiver":null,"user_id":null,"cached_name":"Hsienhsin Chou","cached_surname":"Chou","cached_email":"hsienhsi@andrew.cmu.edu","cached_department":"Architecture","cached_student_class":"5th Year Senior","cache_updated":"2015-12-09T12:45:30.358-05:00","phone_carrier_id":null}]},{"id":33,"name":"The Originals","short_name":"The O's","category":"Non-Building","url":"http://localhost:3000/organizations/33.json","booth_chairs":[]},{"id":35,"name":"Water Polo","short_name":"Polo","category":"Non-Building","url":"http://localhost:3000/organizations/35.json","booth_chairs":[]}]}